{"0":{"long_B":"-0.226506","trip":"149B","stopA_id":"S1001","stopB_id":"S937","lat_A":"5.53562","long_A":"-0.228926","lat_B":"5.53619","distance":275,"time":49},"1":{"long_B":"-0.226506","trip":"476B","stopA_id":"S1001","stopB_id":"S937","lat_A":"5.53562","long_A":"-0.228926","lat_B":"5.53619","distance":275,"time":49},"2":{"long_B":"-0.226506","trip":"524B","stopA_id":"S1001","stopB_id":"S937","lat_A":"5.53562","long_A":"-0.228926","lat_B":"5.53619","distance":275,"time":49},"3":{"long_B":"-0.235723","trip":"244B","stopA_id":"S1153","stopB_id":"S1000","lat_A":"5.53479","long_A":"-0.23291","lat_B":"5.53417","distance":319,"time":44},"4":{"long_B":"-0.228926","trip":"476B","stopA_id":"S1153","stopB_id":"S1001","lat_A":"5.53479","long_A":"-0.23291","lat_B":"5.53562","distance":450,"time":69},"5":{"long_B":"-0.18116","trip":"173B","stopA_id":"S1187","stopB_id":"S1188","lat_A":"5.56795","long_A":"-0.180797","lat_B":"5.56585","distance":255,"time":75},"6":{"long_B":"-0.181676","trip":"416B","stopA_id":"S1188","stopB_id":"S3986","lat_A":"5.56585","long_A":"-0.18116","lat_B":"5.5628","distance":344,"time":102},"7":{"long_B":"-0.181676","trip":"456B","stopA_id":"S1188","stopB_id":"S3986","lat_A":"5.56585","long_A":"-0.18116","lat_B":"5.5628","distance":344,"time":102},"8":{"long_B":"-0.251448","trip":"248B","stopA_id":"S121","stopB_id":"T118","lat_A":"5.5863","long_A":"-0.251435","lat_B":"5.58776","distance":269,"time":85},"9":{"long_B":"-0.239462","trip":"185B","stopA_id":"S1320","stopB_id":"S1321","lat_A":"5.52758","long_A":"-0.236279","lat_B":"5.52712","distance":357,"time":48},"10":{"long_B":"-0.204243","trip":"376B","stopA_id":"S1336","stopB_id":"S1336","lat_A":"5.59239","long_A":"-0.204243","lat_B":"5.59239","distance":0,"time":0},"11":{"long_B":"-0.216396","trip":"219B","stopA_id":"S1370","stopB_id":"S1370","lat_A":"5.57301","long_A":"-0.216396","lat_B":"5.57301","distance":0,"time":0},"12":{"long_B":"-0.281836","trip":"104B","stopA_id":"S14","stopB_id":"S14","lat_A":"5.6877","long_A":"-0.281836","lat_B":"5.6877","distance":0,"time":0},"13":{"long_B":"-0.247032","trip":"048B","stopA_id":"S1535","stopB_id":"T0","lat_A":"5.60076","long_A":"-0.23916","lat_B":"5.6074","distance":3700,"time":737},"14":{"long_B":"-0.176244","trip":"255A","stopA_id":"S1570","stopB_id":"S2220","lat_A":"5.6282","long_A":"-0.176514","lat_B":"5.62086","distance":2693,"time":307},"15":{"long_B":"-0.176244","trip":"256A","stopA_id":"S1570","stopB_id":"S2220","lat_A":"5.6282","long_A":"-0.176514","lat_B":"5.62086","distance":2693,"time":307},"16":{"long_B":"-0.264706","trip":"242B","stopA_id":"S1815","stopB_id":"S1818","lat_A":"5.54649","long_A":"-0.264636","lat_B":"5.5417","distance":533,"time":59},"17":{"long_B":"-0.264706","trip":"246B","stopA_id":"S1815","stopB_id":"S1818","lat_A":"5.54649","long_A":"-0.264636","lat_B":"5.5417","distance":533,"time":59},"18":{"long_B":"-0.265223","trip":"237B","stopA_id":"S1818","stopB_id":"T211","lat_A":"5.5417","long_A":"-0.264706","lat_B":"5.53009","distance":1304,"time":185},"19":{"long_B":"-0.264801","trip":"243A","stopA_id":"S1880","stopB_id":"S2052","lat_A":"5.55035","long_A":"-0.264614","lat_B":"5.55706","distance":1762,"time":291},"20":{"long_B":"-0.264573","trip":"239A","stopA_id":"S1949","stopB_id":"S1877","lat_A":"5.53792","long_A":"-0.264732","lat_B":"5.54375","distance":648,"time":62},"21":{"long_B":"-0.264805","trip":"240A","stopA_id":"S1949","stopB_id":"S1979","lat_A":"5.53792","long_A":"-0.264732","lat_B":"5.54131","distance":1201,"time":172},"22":{"long_B":"-0.264805","trip":"246A","stopA_id":"S1949","stopB_id":"S1979","lat_A":"5.53792","long_A":"-0.264732","lat_B":"5.54131","distance":1201,"time":172},"23":{"long_B":"-0.252326","trip":"318A","stopA_id":"S1993","stopB_id":"S2335","lat_A":"5.60262","long_A":"-0.258491","lat_B":"5.60515","distance":740,"time":72},"24":{"long_B":"-0.255202","trip":"260A","stopA_id":"S210","stopB_id":"S2293","lat_A":"5.53142","long_A":"-0.257723","lat_B":"5.53177","distance":282,"time":43},"25":{"long_B":"-0.264425","trip":"260A","stopA_id":"S2288","stopB_id":"S2289","lat_A":"5.52727","long_A":"-0.266436","lat_B":"5.52897","distance":307,"time":86},"26":{"long_B":"-0.264425","trip":"445A","stopA_id":"S2288","stopB_id":"S2289","lat_A":"5.52727","long_A":"-0.266436","lat_B":"5.52897","distance":307,"time":86},"27":{"long_B":"-0.257723","trip":"260A","stopA_id":"S2291","stopB_id":"S210","lat_A":"5.53112","long_A":"-0.261184","lat_B":"5.53142","distance":392,"time":65},"28":{"long_B":"-0.253713","trip":"260A","stopA_id":"S2293","stopB_id":"S2294","lat_A":"5.53177","long_A":"-0.255202","lat_B":"5.53194","distance":166,"time":35},"29":{"long_B":"-0.246312","trip":"263A","stopA_id":"S2335","stopB_id":"S853","lat_A":"5.60515","long_A":"-0.252326","lat_B":"5.60769","distance":723,"time":79},"30":{"long_B":"-0.24579","trip":"409B","stopA_id":"S2357","stopB_id":"S2357","lat_A":"5.60781","long_A":"-0.24579","lat_B":"5.60781","distance":0,"time":0},"31":{"long_B":"-0.240095","trip":"273B","stopA_id":"S2437","stopB_id":"S2488","lat_A":"5.54825","long_A":"-0.240152","lat_B":"5.55095","distance":300,"time":42},"32":{"long_B":"-0.240148","trip":"277B","stopA_id":"S2488","stopB_id":"S2583","lat_A":"5.55095","long_A":"-0.240095","lat_B":"5.55348","distance":282,"time":60},"33":{"long_B":"-0.264124","trip":"276B","stopA_id":"S2578","stopB_id":"S2311","lat_A":"5.52752","long_A":"-0.266171","lat_B":"5.52922","distance":310,"time":88},"34":{"long_B":"-0.235921","trip":"305B","stopA_id":"S2583","stopB_id":"T75","lat_A":"5.55348","long_A":"-0.240148","lat_B":"5.56507","distance":1482,"time":391},"35":{"long_B":"-0.208197","trip":"226A","stopA_id":"S27","stopB_id":"S26","lat_A":"5.58337","long_A":"-0.208371","lat_B":"5.58489","distance":169,"time":61},"36":{"long_B":"-0.204243","trip":"389B","stopA_id":"S2885","stopB_id":"S1336","lat_A":"5.59468","long_A":"-0.202276","lat_B":"5.59239","distance":335,"time":51},"37":{"long_B":"-0.213015","trip":"334A","stopA_id":"S3142","stopB_id":"S509","lat_A":"5.63561","long_A":"-0.215062","lat_B":"5.63742","distance":372,"time":87},"38":{"long_B":"-0.247032","trip":"055B","stopA_id":"S3162","stopB_id":"T0","lat_A":"5.6079","long_A":"-0.245762","lat_B":"5.6074","distance":5314,"time":897},"39":{"long_B":"-0.247032","trip":"334B","stopA_id":"S3162","stopB_id":"T0","lat_A":"5.6079","long_A":"-0.245762","lat_B":"5.6074","distance":5314,"time":897},"40":{"long_B":"-0.237885","trip":"044A","stopA_id":"S3284","stopB_id":"S3284","lat_A":"5.6437","long_A":"-0.237885","lat_B":"5.6437","distance":0,"time":0},"41":{"long_B":"-0.236597","trip":"123B","stopA_id":"S3288","stopB_id":"S3288","lat_A":"5.64753","long_A":"-0.236597","lat_B":"5.64753","distance":0,"time":0},"42":{"long_B":"-0.198538","trip":"404B","stopA_id":"S3642","stopB_id":"T136","lat_A":"5.59391","long_A":"-0.194835","lat_B":"5.58137","distance":1451,"time":364},"43":{"long_B":"-0.198538","trip":"405B","stopA_id":"S3642","stopB_id":"T136","lat_A":"5.59391","long_A":"-0.194835","lat_B":"5.58137","distance":1451,"time":364},"44":{"long_B":"-0.265466","trip":"114B","stopA_id":"S378","stopB_id":"S378","lat_A":"5.65777","long_A":"-0.265466","lat_B":"5.65777","distance":0,"time":0},"45":{"long_B":"-0.180332","trip":"416A","stopA_id":"S3974","stopB_id":"S3975","lat_A":"5.56795","long_A":"-0.180752","lat_B":"5.57059","distance":297,"time":41},"46":{"long_B":"-0.182212","trip":"456B","stopA_id":"S3986","stopB_id":"S3989","lat_A":"5.5628","long_A":"-0.181676","lat_B":"5.5596","distance":361,"time":134},"47":{"long_B":"-0.182718","trip":"456B","stopA_id":"S3989","stopB_id":"S1189","lat_A":"5.5596","long_A":"-0.182212","lat_B":"5.55636","distance":366,"time":75},"48":{"long_B":"-0.281729","trip":"104A","stopA_id":"S415","stopB_id":"S415","lat_A":"5.68773","long_A":"-0.281729","lat_B":"5.68773","distance":0,"time":0},"49":{"long_B":"-0.240265","trip":"446A","stopA_id":"S4320","stopB_id":"S4320","lat_A":"5.55152","long_A":"-0.240265","lat_B":"5.55152","distance":0,"time":0},"50":{"long_B":"-0.216939","trip":"224A","stopA_id":"S466","stopB_id":"S466","lat_A":"5.59127","long_A":"-0.216939","lat_B":"5.59127","distance":0,"time":0},"51":{"long_B":"-0.2574","trip":"488B","stopA_id":"S4714","stopB_id":"T4715","lat_A":"5.55239","long_A":"-0.251108","lat_B":"5.54954","distance":886,"time":170},"52":{"long_B":"-0.251367","trip":"524A","stopA_id":"S4869","stopB_id":"S4870","lat_A":"5.53883","long_A":"-0.246567","lat_B":"5.53983","distance":634,"time":95},"53":{"long_B":"-0.213015","trip":"351A","stopA_id":"S494","stopB_id":"S509","lat_A":"5.6413","long_A":"-0.205381","lat_B":"5.63742","distance":960,"time":154},"54":{"long_B":"-0.179331","trip":"100A","stopA_id":"S517","stopB_id":"T497","lat_A":"5.64064","long_A":"-0.179353","lat_B":"5.64911","distance":1091,"time":133},"55":{"long_B":"-0.237586","trip":"015B","stopA_id":"S5246","stopB_id":"S5246","lat_A":"5.6444","long_A":"-0.237586","lat_B":"5.6444","distance":0,"time":0},"56":{"long_B":"-0.237586","trip":"044B","stopA_id":"S5246","stopB_id":"S5246","lat_A":"5.6444","long_A":"-0.237586","lat_B":"5.6444","distance":0,"time":0},"57":{"long_B":"-0.265315","trip":"019A","stopA_id":"S5435","stopB_id":"S5435","lat_A":"5.65777","long_A":"-0.265315","lat_B":"5.65777","distance":0,"time":0},"58":{"long_B":"-0.1446","trip":"023A","stopA_id":"S5537","stopB_id":"S5535","lat_A":"5.56937","long_A":"0.147489","lat_B":"5.5651"},"59":{"long_B":"-0.236171","trip":"026B","stopA_id":"S5564","stopB_id":"S5564","lat_A":"5.59931","long_A":"-0.236171","lat_B":"5.59931","distance":0,"time":0},"60":{"long_B":"-0.207327","trip":"061B","stopA_id":"S567","stopB_id":"S569","lat_A":"5.60501","long_A":"-0.203651","lat_B":"5.60749","distance":491,"time":60},"61":{"long_B":"-0.207327","trip":"076B","stopA_id":"S567","stopB_id":"S569","lat_A":"5.60501","long_A":"-0.203651","lat_B":"5.60749","distance":491,"time":60},"62":{"long_B":"-0.207327","trip":"103B","stopA_id":"S567","stopB_id":"S569","lat_A":"5.60501","long_A":"-0.203651","lat_B":"5.60749","distance":491,"time":60},"63":{"long_B":"-0.022384","trip":"008A","stopA_id":"S6164","stopB_id":"S6164","lat_A":"5.6792","long_A":"-0.022384","lat_B":"5.6792","distance":0,"time":0},"64":{"long_B":"-0.245762","trip":"334B","stopA_id":"S752","stopB_id":"S3162","lat_A":"5.61281","long_A":"-0.226714","lat_B":"5.6079","distance":9525,"time":1082},"65":{"long_B":"-0.14552","trip":"118B","stopA_id":"S775","stopB_id":"S775","lat_A":"5.56666","long_A":"-0.14552","lat_B":"5.56666","distance":0,"time":0},"66":{"long_B":"-0.196282","trip":"120B","stopA_id":"S805","stopB_id":"S805","lat_A":"5.68987","long_A":"-0.196282","lat_B":"5.68987","distance":0,"time":0},"67":{"long_B":"-0.245779","trip":"122A","stopA_id":"S855","stopB_id":"S855","lat_A":"5.60809","long_A":"-0.245779","lat_B":"5.60809","distance":0,"time":0},"68":{"long_B":"-0.245779","trip":"122A","stopA_id":"S855","stopB_id":"S855","lat_A":"5.60809","long_A":"-0.245779","lat_B":"5.60809","distance":0,"time":0},"69":{"long_B":"-0.246252","trip":"270B","stopA_id":"S934","stopB_id":"S934","lat_A":"5.53569","long_A":"-0.246252","lat_B":"5.53569","distance":0,"time":0},"70":{"long_B":"-0.23291","trip":"170B","stopA_id":"S937","stopB_id":"S1153","lat_A":"5.53619","long_A":"-0.226506","lat_B":"5.53479","distance":726,"time":112},"71":{"long_B":"-0.23291","trip":"244B","stopA_id":"S937","stopB_id":"S1153","lat_A":"5.53619","long_A":"-0.226506","lat_B":"5.53479","distance":726,"time":112},"72":{"long_B":"-0.246567","trip":"524A","stopA_id":"S991","stopB_id":"S4869","lat_A":"5.53561","long_A":"-0.246314","lat_B":"5.53883","distance":392,"time":67},"73":{"long_B":"-0.238147","trip":"098B","stopA_id":"T0","stopB_id":"S486","lat_A":"5.6074","long_A":"-0.247032","lat_B":"5.60912","distance":1004,"time":60},"74":{"long_B":"-0.172071","trip":"339A","stopA_id":"T0","stopB_id":"T534","lat_A":"5.6074","long_A":"-0.247032","lat_B":"5.67642","distance":15318,"time":1298},"75":{"long_B":"-0.264732","trip":"240A","stopA_id":"T211","stopB_id":"S1949","lat_A":"5.53009","long_A":"-0.265223","lat_B":"5.53792","distance":890,"time":159},"76":{"long_B":"-0.264732","trip":"246A","stopA_id":"T211","stopB_id":"S1949","lat_A":"5.53009","long_A":"-0.265223","lat_B":"5.53792","distance":890,"time":159},"77":{"long_B":"-0.226506","trip":"447B","stopA_id":"T244","stopB_id":"S937","lat_A":"5.54863","long_A":"-0.201709","lat_B":"5.53619","distance":3669,"time":652},"78":{"long_B":"-0.166247","trip":"442A","stopA_id":"T4238","stopB_id":"T2022","lat_A":"5.64075","long_A":"-0.176294","lat_B":"5.64198","distance":1159,"time":240}}